{
    "CoreStore": [
        {
            "name": "c1",
            "speedup": 1,
            "device": "d1"
        },
        {
            "name": "c2",
            "speedup": 1,
            "device": "d1"
        },
        {
            "name": "c3",
            "speedup": 1,
            "device": "d1"
        },
        {
            "name": "c4",
            "speedup": 1,
            "device": "d1"
        }
    ],
    "DeviceStore": [
        {
            "name": "d1",
            "sppedup": 1,
            "delays": [
                {
                    "protocol": "tcp",
                    "acdt": 500000,
                    "bcdt": 500000,
                    "wcdt": 500000,
                    "distribution": "Normal"
                }
            ]
        }
    ],
    "NetworkDelayStore": [],
    "EntityStore": [
        {
            "name": "t1",
            "type": "task",
            "acet": 900161,
            "bcet": 900161,
            "wcet": 900161,
            "core": null,
            "distribution": "Normal",
            "inputs": [
                "in1"
            ],
            "outputs": [
                "out1"
            ],
            "priority": null,
            "activationOffset": 0,
            "initialOffset": 1498972,
            "period": 5000000,
            "duration": 2808375
        }
    ],
    "DependencyStore": [],
    "EntityInstancesStore": [
        {
            "name": "t1",
            "type": "task",
            "initialOffset": 1498972,
            "value": [
                {
                    "instance": 0,
                    "periodStartTime": 1498972,
                    "periodEndTime": 6498972,
                    "letStartTime": 1498972,
                    "letEndTime": 4307347,
                    "executionTime": 900161,
                    "currentCore": {
                        "name": "c1",
                        "speedup": 1,
                        "device": "d1"
                    },
                    "executionIntervals": [
                        {
                            "core": "c1",
                            "endTime": 2399133.0,
                            "startTime": 1498972.0
                        }
                    ]
                },
                {
                    "instance": 1,
                    "periodStartTime": 6498972,
                    "periodEndTime": 11498972,
                    "letStartTime": 6498972,
                    "letEndTime": 9307347,
                    "executionTime": 900161,
                    "currentCore": {
                        "name": "c1",
                        "speedup": 1,
                        "device": "d1"
                    },
                    "executionIntervals": [
                        {
                            "core": "c1",
                            "endTime": 7399133.0,
                            "startTime": 6498972.0
                        }
                    ]
                },
                {
                    "instance": 2,
                    "periodStartTime": 11498972,
                    "periodEndTime": 16498972,
                    "letStartTime": 11498972,
                    "letEndTime": 14307347,
                    "executionTime": 900161,
                    "currentCore": {
                        "name": "c1",
                        "speedup": 1,
                        "device": "d1"
                    },
                    "executionIntervals": [
                        {
                            "core": "c1",
                            "endTime": 12399133.0,
                            "startTime": 11498972.0
                        }
                    ]
                },
                {
                    "instance": 3,
                    "periodStartTime": 16498972,
                    "periodEndTime": 21498972,
                    "letStartTime": 16498972,
                    "letEndTime": 19307347,
                    "executionTime": 900161,
                    "currentCore": {
                        "name": "c1",
                        "speedup": 1,
                        "device": "d1"
                    },
                    "executionIntervals": [
                        {
                            "core": "c1",
                            "endTime": 17399133.0,
                            "startTime": 16498972.0
                        }
                    ]
                },
                {
                    "instance": 4,
                    "periodStartTime": 21498972,
                    "periodEndTime": 26498972,
                    "letStartTime": 21498972,
                    "letEndTime": 24307347,
                    "executionTime": 900161,
                    "currentCore": {
                        "name": "c1",
                        "speedup": 1,
                        "device": "d1"
                    },
                    "executionIntervals": [
                        {
                            "core": "c1",
                            "endTime": 22399133.0,
                            "startTime": 21498972.0
                        }
                    ]
                },
                {
                    "instance": 5,
                    "periodStartTime": 26498972,
                    "periodEndTime": 31498972,
                    "letStartTime": 26498972,
                    "letEndTime": 29307347,
                    "executionTime": 900161,
                    "currentCore": {
                        "name": "c1",
                        "speedup": 1,
                        "device": "d1"
                    },
                    "executionIntervals": [
                        {
                            "core": "c1",
                            "endTime": 27399133.0,
                            "startTime": 26498972.0
                        }
                    ]
                },
                {
                    "instance": 6,
                    "periodStartTime": 31498972,
                    "periodEndTime": 36498972,
                    "letStartTime": 31498972,
                    "letEndTime": 34307347,
                    "executionTime": 900161,
                    "currentCore": {
                        "name": "c1",
                        "speedup": 1,
                        "device": "d1"
                    },
                    "executionIntervals": [
                        {
                            "core": "c1",
                            "endTime": 32399133.0,
                            "startTime": 31498972.0
                        }
                    ]
                },
                {
                    "instance": 7,
                    "periodStartTime": 36498972,
                    "periodEndTime": 41498972,
                    "letStartTime": 36498972,
                    "letEndTime": 39307347,
                    "executionTime": 900161,
                    "currentCore": {
                        "name": "c1",
                        "speedup": 1,
                        "device": "d1"
                    },
                    "executionIntervals": [
                        {
                            "core": "c1",
                            "endTime": 37399133.0,
                            "startTime": 36498972.0
                        }
                    ]
                },
                {
                    "instance": 8,
                    "periodStartTime": 41498972,
                    "periodEndTime": 46498972,
                    "letStartTime": 41498972,
                    "letEndTime": 44307347,
                    "executionTime": 900161,
                    "currentCore": {
                        "name": "c1",
                        "speedup": 1,
                        "device": "d1"
                    },
                    "executionIntervals": [
                        {
                            "core": "c1",
                            "endTime": 42399133.0,
                            "startTime": 41498972.0
                        }
                    ]
                },
                {
                    "instance": 9,
                    "periodStartTime": 46498972,
                    "periodEndTime": 51498972,
                    "letStartTime": 46498972,
                    "letEndTime": 49307347,
                    "executionTime": 900161,
                    "currentCore": {
                        "name": "c1",
                        "speedup": 1,
                        "device": "d1"
                    },
                    "executionIntervals": [
                        {
                            "core": "c1",
                            "endTime": 47399133.0,
                            "startTime": 46498972.0
                        }
                    ]
                },
                {
                    "instance": 10,
                    "periodStartTime": 51498972,
                    "periodEndTime": 56498972,
                    "letStartTime": 51498972,
                    "letEndTime": 54307347,
                    "executionTime": 900161,
                    "currentCore": {
                        "name": "c1",
                        "speedup": 1,
                        "device": "d1"
                    },
                    "executionIntervals": [
                        {
                            "core": "c1",
                            "endTime": 52399133.0,
                            "startTime": 51498972.0
                        }
                    ]
                },
                {
                    "instance": 11,
                    "periodStartTime": 56498972,
                    "periodEndTime": 61498972,
                    "letStartTime": 56498972,
                    "letEndTime": 59307347,
                    "executionTime": 900161,
                    "currentCore": {
                        "name": "c1",
                        "speedup": 1,
                        "device": "d1"
                    },
                    "executionIntervals": [
                        {
                            "core": "c1",
                            "endTime": 57399133.0,
                            "startTime": 56498972.0
                        }
                    ]
                }
            ]
        }
    ]
}